poetry_plugin_compose/__init__.py
poetry_plugin_compose/compose_command.py
poetry_plugin_compose/composed_command_list.py
poetry_plugin_compose/composed_commands/__init__.py
poetry_plugin_compose/composed_commands/composed_add_command.py
poetry_plugin_compose/composed_commands/composed_build_command.py
poetry_plugin_compose/composed_commands/composed_check_command.py
poetry_plugin_compose/composed_commands/composed_command.py
poetry_plugin_compose/composed_commands/composed_command_utils.py
poetry_plugin_compose/composed_commands/composed_install_command.py
poetry_plugin_compose/composed_commands/composed_lock_command.py
poetry_plugin_compose/composed_commands/composed_publish_command.py
poetry_plugin_compose/composed_commands/composed_remove_command.py
poetry_plugin_compose/composed_commands/composed_run_command.py
poetry_plugin_compose/composed_commands/composed_update_command.py
poetry_plugin_compose/composed_commands/dependency_order_command.py
poetry_plugin_compose/composed_commands/package_filter.py
poetry_plugin_compose/composed_commands/sub_command_runner.py
poetry_plugin_compose/packages/__init__.py
poetry_plugin_compose/packages/build_dependency_graph.py
poetry_plugin_compose/packages/build_natural_order.py
poetry_plugin_compose/packages/discover_packages.py
poetry_plugin_compose/packages/get_package_dependencies.py
poetry_plugin_compose/packages/get_package_descriptor.py
poetry_plugin_compose/packages/sub_package_contains.py
poetry_plugin_compose/packages/sub_package_has_dependency.py
poetry_plugin_compose/plugin.py
poetry_plugin_compose/toposort/__init__.py
poetry_plugin_compose/toposort/graph.py
poetry_plugin_compose-0.1.2.dist-info/METADATA
poetry_plugin_compose-0.1.2.dist-info/WHEEL
poetry_plugin_compose-0.1.2.dist-info/entry_points.txt
poetry_plugin_compose-0.1.2.dist-info/RECORD
