Metadata-Version: 2.1
Name: poetry-plugin-compose
Version: 0.1.2
Summary: 
Author: Max
Author-email: maximilienlarue@gmail.com
Requires-Python: >=3.9,<4.0
Classifier: Programming Language :: Python :: 3
Classifier: Programming Language :: Python :: 3.9
Classifier: Programming Language :: Python :: 3.10
Classifier: Programming Language :: Python :: 3.11
Requires-Dist: poetry (>=1.4.2,<2.0.0)
Requires-Dist: tomli (>=2.0.1,<3.0.0)
